pihome/server.py
pihome-1.0.3.dist-info/METADATA
pihome-1.0.3.dist-info/WHEEL
pihome-1.0.3.dist-info/top_level.txt
pihome-1.0.3.dist-info/RECORD
